jailbreakbench/__init__.py
jailbreakbench/artifact.py
jailbreakbench/classifier.py
jailbreakbench/config.py
jailbreakbench/dataset.py
jailbreakbench/submission.py
jailbreakbench/vllm_server.py
jailbreakbench/defenses/__init__.py
jailbreakbench/defenses/base_defense.py
jailbreakbench/defenses/defenses_registry.py
jailbreakbench/defenses/erase_and_check.py
jailbreakbench/defenses/perplexity_filter.py
jailbreakbench/defenses/remove_non_dictionary.py
jailbreakbench/defenses/smooth_llm.py
jailbreakbench/defenses/synonym_substitution.py
jailbreakbench/defenses/defenselib/__init__.py
jailbreakbench/defenses/defenselib/defense_hparams.py
jailbreakbench/defenses/defenselib/perturbations.py
jailbreakbench/llm/__init__.py
jailbreakbench/llm/dummy_vllm.py
jailbreakbench/llm/litellm.py
jailbreakbench/llm/llm_output.py
jailbreakbench/llm/llm_wrapper.py
jailbreakbench/llm/vllm.py
jailbreakbench/plotting/plot_source_breakdown.py
jailbreakbench-1.0.0.dist-info/METADATA
jailbreakbench-1.0.0.dist-info/WHEEL
jailbreakbench-1.0.0.dist-info/licenses/LICENSE
jailbreakbench-1.0.0.dist-info/RECORD
