Metadata-Version: 2.3
Name: jailbreakbench
Version: 1.0.0
Summary:  An Open Robustness Benchmark for Jailbreaking Language Models
Project-URL: Homepage, https://jailbreakbench.github.io
Project-URL: Repository, https://github.com/JailbreakBench/jailbreakbench.git
Project-URL: Issues, https://github.com/JailbreakBench/jailbreakbench/issues
License: MIT License
License-File: LICENSE
Keywords: benchmark,jailbreak,jailbreakbench,llms,machine learning,security
Classifier: Development Status :: 4 - Beta
Classifier: Environment :: GPU
Classifier: Intended Audience :: Developers
Classifier: Intended Audience :: Science/Research
Classifier: License :: OSI Approved :: MIT License
Classifier: Programming Language :: Python :: 3
Classifier: Programming Language :: Python :: 3.10
Classifier: Programming Language :: Python :: 3.11
Classifier: Programming Language :: Python :: 3.12
Classifier: Topic :: Scientific/Engineering :: Artificial Intelligence
Classifier: Topic :: Security
Requires-Python: <3.12,>=3.10
Requires-Dist: datasets>=2.19.2
Requires-Dist: litellm>=1.20.0
Requires-Dist: nltk>=3.8.1
Requires-Dist: pandas<3.0.0,>=2.2.0
Requires-Dist: protobuf<5.0.0,>=4.25.3
Requires-Dist: pydantic<3.0.0,>=2.6.1
Requires-Dist: requests<3.0.0,>=2.31.0
Requires-Dist: sentencepiece<1.0.0,>=0.2.0
Requires-Dist: setuptools>=61.0
Requires-Dist: tenacity<9.0.0,>=8.2.3
Requires-Dist: torch<3.0.0,>=2.0.0
Requires-Dist: tqdm>=4.66.2
Requires-Dist: transformers<5.0.0,>=4.38.0
Requires-Dist: types-requests<3.0.0,>=2.31.0
Requires-Dist: wordfreq>=3.1.1
Provides-Extra: vllm
Requires-Dist: accelerate<1.0.0,>=0.27.2; extra == 'vllm'
Requires-Dist: click<9.0.0,>=8.1.7; extra == 'vllm'
Requires-Dist: vllm~=0.3.2; extra == 'vllm'
